ccalign/__init__.py
ccalign/alignment.py
ccalign/audio_transcription.py
ccalign/utils.py
ccalign-0.0.1.dist-info/LICENSE
ccalign-0.0.1.dist-info/METADATA
ccalign-0.0.1.dist-info/WHEEL
ccalign-0.0.1.dist-info/top_level.txt
ccalign-0.0.1.dist-info/RECORD
