Metadata-Version: 2.1
Name: ccalign
Version: 0.0.1
Summary: A sentence-level text-audio alignment tool for conference calls.
Home-page: https://github.com/j-ewertz/ccalign
Author: Jonas Ewertz
Author-email: jonas.ewertz@ikf.rub.de
License: MIT
Classifier: Programming Language :: Python :: 3
Classifier: License :: OSI Approved :: MIT License
Classifier: Operating System :: OS Independent
Requires-Python: >=3.8
License-File: LICENSE
Requires-Dist: setuptools>=65
Requires-Dist: transformers
Requires-Dist: fastparquet==2024.11.0
Requires-Dist: inflect==7.4.0
Requires-Dist: Levenshtein==0.26.1
Requires-Dist: pyarrow==18.1.0
Requires-Dist: pydub==0.25.1
Requires-Dist: python-Levenshtein==0.26.1
Requires-Dist: regex==2024.11.6
Requires-Dist: tqdm==4.67.1
Requires-Dist: faster-whisper==1.0.0
Requires-Dist: ctranslate2==4.4.0
Requires-Dist: nltk
Requires-Dist: datasets
